[
  {
    "NOME": "KEZIA VENUTE ROCHA DOS SANTOS",
    "CLASSIFICACAO": "4"
  },
  {
    "NOME": "RHAEANNY FIGUEIREDO DA SILVA E SILVA",
    "CLASSIFICACAO": "16"
  },
  {
    "NOME": "KATLEN DE MELO LIRA",
    "CLASSIFICACAO": "19"
  },
  {
    "NOME": "BEATRIZ OLIVEIRA NASCIMENTO",
    "CLASSIFICACAO": "(OVR)26"
  },
  {
    "NOME": "GUILHERME DE MOURA GOUVEIA",
    "CLASSIFICACAO": "(OVR)32"
  },
  {
    "NOME": "ENAILE SCANFELA DINIZ",
    "CLASSIFICACAO": "34"
  },
  {
    "NOME": "MIRIA SANTOS DE PAIVA",
    "CLASSIFICACAO": "38ºCG e 2ºVR"
  },
  {
    "NOME": "CAMILLA CHRISTIE VITURINO MARTINS",
    "CLASSIFICACAO": "40"
  },
  {
    "NOME": "CAROLINE TARANTO DE ASSIS",
    "CLASSIFICACAO": "43"
  },
  {
    "NOME": "MARCELLA MONIQUE GUIMARAES MEDEIROS",
    "CLASSIFICACAO": "54"
  },
  {
    "NOME": "YASMIN DE SOUZA RIBEIRO",
    "CLASSIFICACAO": "55"
  },
  {
    "NOME": "THAIS DA SILVA CORDEIRO",
    "CLASSIFICACAO": "57"
  },
  {
    "NOME": "INGRID RIBEIRO PEREIRA",
    "CLASSIFICACAO": "60ºCG e 6ºVR"
  },
  {
    "NOME": "DANIEL FERREIRA DE MAGALHAES",
    "CLASSIFICACAO": "61ºCG e 7ºVR"
  },
  {
    "NOME": "RAIRA DA FONSECA ANTONIO BARROS",
    "CLASSIFICACAO": "65ºCG e 9ºVR"
  },
  {
    "NOME": "CAROLINA PEREIRA CORREA DA SILVA",
    "CLASSIFICACAO": "66"
  },
  {
    "NOME": "ESTER NEVES DE SOUZA",
    "CLASSIFICACAO": "69ºCG e 12ºVR"
  },
  {
    "NOME": "MARCELLY ARIANY SILVA DOS SANTOS",
    "CLASSIFICACAO": "74"
  },
  {
    "NOME": "LORRANE COUTINHO BARACAL",
    "CLASSIFICACAO": "83"
  },
  {
    "NOME": "ISABELA MARQUES REIS DE QUEIROZ",
    "CLASSIFICACAO": "84ºCG e 15ºVR"
  },
  {
    "NOME": "SABRINA PADUAM DE ALCANTARA",
    "CLASSIFICACAO": "96"
  },
  {
    "NOME": "YRIS VITORIA DOS SANTOS NUNES",
    "CLASSIFICACAO": "98ºCG e 20ºVR"
  },
  {
    "NOME": "AMANDA NECHAEFF PIMENTA OLIVEIRA",
    "CLASSIFICACAO": "105"
  },
  {
    "NOME": "MARCELE SANTOS GIOLITO",
    "CLASSIFICACAO": "106"
  },
  {
    "NOME": "THAIS MALTA DOS REIS",
    "CLASSIFICACAO": "112"
  },
  {
    "NOME": "MYLENA DE JESUS DOS REIS",
    "CLASSIFICACAO": "122ºCG e 28ºVR"
  },
  {
    "NOME": "EVELYN SILVA MAIA",
    "CLASSIFICACAO": "124"
  },
  {
    "NOME": "MAISSA FREIRE DE OLIVEIRA",
    "CLASSIFICACAO": "125"
  },
  {
    "NOME": "RAYANE CRISTOVAO MOREIRA",
    "CLASSIFICACAO": "126"
  },
  {
    "NOME": "NATHALIA CAROLINE RAMOS MACHADO DOS SANTOS",
    "CLASSIFICACAO": "127ºCG e 29ºVR"
  },
  {
    "NOME": "LORHANNY DA SILVA REIS",
    "CLASSIFICACAO": "133ºCG e 30ºVR"
  },
  {
    "NOME": "JORLEANDRO COSTA LEITE",
    "CLASSIFICACAO": "135ºCG e 31ºVR"
  },
  {
    "NOME": "SUELEN DRUMOND DE SOUZA",
    "CLASSIFICACAO": "137ºCG e 32ºVR"
  },
  {
    "NOME": "SABRINA SILVA DA PAIXAO",
    "CLASSIFICACAO": "140"
  },
  {
    "NOME": "HEMILLY ALMEIDA PINHEIRO DA SILVA",
    "CLASSIFICACAO": "142ºCG e 34ºVR"
  },
  {
    "NOME": "STHEFANE RODRIGUES FIGUEIREDO",
    "CLASSIFICACAO": "145ºCG e 36ºVR"
  },
  {
    "NOME": "RAYSSA CIPRIANO DA SILVA BRAGA",
    "CLASSIFICACAO": "148ºCG e 37ºVR"
  },
  {
    "NOME": "GABRIELA VITORIA DE SOUZA MOTA",
    "CLASSIFICACAO": "152"
  },
  {
    "NOME": "LARISSA LACERDA DE MENDONCA",
    "CLASSIFICACAO": "157"
  },
  {
    "NOME": "ISABELLA GRIEBELER CASTRO",
    "CLASSIFICACAO": "160"
  },
  {
    "NOME": "LETICIA VIDAL DE FREITAS MENDES",
    "CLASSIFICACAO": "161"
  },
  {
    "NOME": "JULIANA MEDEIROS MARTINS",
    "CLASSIFICACAO": "166ºCG e 40ºVR"
  },
  {
    "NOME": "JHENIFFER VALENTIM SILVESTRE COSTA",
    "CLASSIFICACAO": "167"
  },
  {
    "NOME": "ANGELA CRISTHINE PINHEIRO SILVA",
    "CLASSIFICACAO": "170"
  },
  {
    "NOME": "JOSILAINE NUNES ALVES",
    "CLASSIFICACAO": "171ºCG e 42ºVR"
  },
  {
    "NOME": "LIDIANE DRUMOND MACARIO",
    "CLASSIFICACAO": "173ºCG e 44ºVR"
  },
  {
    "NOME": "JOAO VICTOR VELASQUES KIMEL",
    "CLASSIFICACAO": "179"
  },
  {
    "NOME": "ANA BEATRIZ BARCELLOS CARDOSO DA ROSA",
    "CLASSIFICACAO": "185ºCG e 51ºVR"
  },
  {
    "NOME": "HEIDY CRISTINA RODRIGUES BARRETO",
    "CLASSIFICACAO": "194ºCG e 54ºVR"
  },
  {
    "NOME": "FRANCIELE RODRIGUES VIRTUOSO DE SOUZA",
    "CLASSIFICACAO": "200"
  },
  {
    "NOME": "CAROLINA REGINA DA SILVA GARCIA",
    "CLASSIFICACAO": "202ºCG e 57ºVR"
  },
  {
    "NOME": "WILLISSON SILVA FERREIRA",
    "CLASSIFICACAO": "204ºCG e 58ºVR"
  },
  {
    "NOME": "LAIS RODRIGUES DE ARAUJO MARTINS COSTA",
    "CLASSIFICACAO": "209"
  },
  {
    "NOME": "GABRIELA DO VALE MATTOS",
    "CLASSIFICACAO": "215ºCG e 64ºVR"
  },
  {
    "NOME": "AGDA APARECIDA AMANCIO DIAS",
    "CLASSIFICACAO": "222"
  },
  {
    "NOME": "RAISSA DE OLIVEIRA PEREIRA",
    "CLASSIFICACAO": "223ºCG e 67ºVR"
  },
  {
    "NOME": "ERIKA SALES DE ALMEIDA GABY",
    "CLASSIFICACAO": "228ºCG e 68ºVR"
  },
  {
    "NOME": "FERNANDA VIVIANE DA CRUZ SANTOS",
    "CLASSIFICACAO": "230ºCG e 70ºVR"
  },
  {
    "NOME": "JULIANA LIMA DOS SANTOS",
    "CLASSIFICACAO": "231"
  },
  {
    "NOME": "JHONTHANAS BORGES DA SILVA E SILVA",
    "CLASSIFICACAO": "232ºCG e 71ºVR"
  },
  {
    "NOME": "ANA PAULA ANDRADE",
    "CLASSIFICACAO": "233"
  },
  {
    "NOME": "JOICE CANTARINO DA COSTA",
    "CLASSIFICACAO": "239"
  },
  {
    "NOME": "GABRIELLE QUADROS DE SOUZA",
    "CLASSIFICACAO": "250"
  },
  {
    "NOME": "DEBORA RIBEIRO DOS SANTOS",
    "CLASSIFICACAO": "256"
  },
  {
    "NOME": "RAYNARA GOMES DA SILVA",
    "CLASSIFICACAO": "261"
  },
  {
    "NOME": "THALIA DA SILVA SOUZA",
    "CLASSIFICACAO": "262"
  },
  {
    "NOME": "MARIA LUIZA DE OLIVEIRA SILVA",
    "CLASSIFICACAO": "276"
  },
  {
    "NOME": "RAISSA GOMES DE SOUZA",
    "CLASSIFICACAO": "279"
  },
  {
    "NOME": "KELLEN CRISTINA DOS SANTOS OLIVEIRA",
    "CLASSIFICACAO": "280"
  },
  {
    "NOME": "ELLEN CHRISTINE PEREIRA DO NASCIMENTO",
    "CLASSIFICACAO": "289"
  },
  {
    "NOME": "REBECA SOUTO DE JESUS AUGUSTO",
    "CLASSIFICACAO": "295"
  },
  {
    "NOME": "ISIS ALVES DE SOUZA",
    "CLASSIFICACAO": "298ºCG e 86ºVR"
  },
  {
    "NOME": "FABRICIA OLIVEIRA SOUZA",
    "CLASSIFICACAO": "300"
  },
  {
    "NOME": "JHENNYFER OLIVEIRA DOS SANTOS",
    "CLASSIFICACAO": "305ºCG e 87ºVR"
  },
  {
    "NOME": "LARISSA GABRIELA GOMES DO NASCIMENTO",
    "CLASSIFICACAO": "310"
  },
  {
    "NOME": "EMANUELLY SOARES BARBOSA DA SILVA",
    "CLASSIFICACAO": "317"
  },
  {
    "NOME": "KATHLEN VITORIA DE LIMA NOBRE",
    "CLASSIFICACAO": "320"
  },
  {
    "NOME": "FERNANDA DOMINGUES DA ROCHA",
    "CLASSIFICACAO": "323"
  },
  {
    "NOME": "ADRIELLY ALVES DA SILVA",
    "CLASSIFICACAO": "330"
  },
  {
    "NOME": "REBECA BARBOSA DA SILVA",
    "CLASSIFICACAO": "335"
  },
  {
    "NOME": "THAIS TEIXEIRA DA SILVA",
    "CLASSIFICACAO": "345"
  },
  {
    "NOME": "THAIS ADRIELLE DA SILVA MOREIRA",
    "CLASSIFICACAO": "346"
  },
  {
    "NOME": "BRUNA RAMOS CRESPO",
    "CLASSIFICACAO": "359"
  },
  {
    "NOME": "LARISSA MARTINS DA MOTA",
    "CLASSIFICACAO": "366"
  },
  {
    "NOME": "THAYNA SILVA FERREIRA",
    "CLASSIFICACAO": "374ºCG e 108ºVR"
  },
  {
    "NOME": "GABRIELY GOMES CLIMACO BRITES",
    "CLASSIFICACAO": "377"
  },
  {
    "NOME": "VITORIA DE MELO QUIXABA",
    "CLASSIFICACAO": "383ºCG e 111ºVR"
  },
  {
    "NOME": "ROMULO CARLOS RIBEIRO DA SILVA",
    "CLASSIFICACAO": "387ºCG e 113ºVR"
  },
  {
    "NOME": "YASMIM DA SILVA SAO TIAGO",
    "CLASSIFICACAO": "392"
  },
  {
    "NOME": "ADRIELLE DE SOUZA JOSE",
    "CLASSIFICACAO": "397ºCG e 116ºVR"
  },
  {
    "NOME": "LETICIA FERREIRA DOS SANTOS",
    "CLASSIFICACAO": "400ºCG e 118ºVR"
  },
  {
    "NOME": "INGRID MARTINS DE OLIVEIRA",
    "CLASSIFICACAO": "401ºCG e 119ºVR"
  },
  {
    "NOME": "AMANDA MENDES DA SILVA DE LIMA",
    "CLASSIFICACAO": "415"
  },
  {
    "NOME": "CRISTINE ESTRELLA MOREIRA DOS SANTOS",
    "CLASSIFICACAO": "420"
  },
  {
    "NOME": "CAROLINE MONTEIRO RIBEIRO",
    "CLASSIFICACAO": "428"
  },
  {
    "NOME": "MARIA TEREZA DE SOUZA VIANNA",
    "CLASSIFICACAO": "432ºCG e 128ºVR"
  },
  {
    "NOME": "LARISSA SILVA DOS SANTOS",
    "CLASSIFICACAO": "438"
  },
  {
    "NOME": "HANNA BEATRIZ CORREA DA ROCHA",
    "CLASSIFICACAO": "442"
  },
  {
    "NOME": "LARISSA RANGEL DE OLIVEIRA",
    "CLASSIFICACAO": "445"
  },
  {
    "NOME": "GIOVANA PEREIRA DE PAULA",
    "CLASSIFICACAO": "446ºCG e 130ºVR"
  },
  {
    "NOME": "ANA CAROLINA DO ESPIRITO SANTO POMPEU",
    "CLASSIFICACAO": "452ºCG e 132ºVR"
  },
  {
    "NOME": "FELIX AUGUSTO DA SILVA SOARES SANTIAGO",
    "CLASSIFICACAO": "460ºCG e 134ºVR"
  },
  {
    "NOME": "JULIA GABRIELLA BORGES DE SOUZA RAINHA",
    "CLASSIFICACAO": "468ºCG e 137ºVR"
  },
  {
    "NOME": "ANDRESSA CARVALHO DE BARROS",
    "CLASSIFICACAO": "473"
  },
  {
    "NOME": "JULIA GONCALVES REIS SANTOS",
    "CLASSIFICACAO": "489ºCG e 140ºVR"
  },
  {
    "NOME": "LUANA DA SILVA ESTEVAO",
    "CLASSIFICACAO": "491"
  },
  {
    "NOME": "JOICE DA SILVA TEIXEIRA",
    "CLASSIFICACAO": "496"
  }
]